AUTHORS
LICENSE
MANIFEST.in
README.md
RELEASE-VERSION
setup.py
contrib/__init__.py
contrib/version.py
docs/html/Riverbed_Cascade_Gateway_REST_API_v1_1.html
docs/html/Riverbed_Cascade_Profiler_Common_REST_API_v1_0.html
docs/html/Riverbed_Cascade_Profiler_REST_API_v1_0.html
docs/html/Riverbed_Cascade_Profiler_REST_API_v1_1.html
docs/html/Riverbed_Cascade_Sensor_REST_API_v1_1.html
docs/html/Riverbed_Cascade_Shark_Common_REST_API_v1_0.html
docs/html/Riverbed_Cascade_Shark_Common_REST_API_v1_0_DRAFT_0_2.html
docs/html/Riverbed_Cascade_Shark_Common_REST_API_v1_1.html
docs/html/Riverbed_Cascade_Shark_REST_API_v4_0_DRAFT_0_2.html
docs/html/Riverbed_Cascade_Shark_REST_API_v5_0.html
docs/html/Riverbed_Cascade_Shark_REST_API_v5_1.html
docs/html/background.html
docs/html/common.html
docs/html/conn.html
docs/html/extras.html
docs/html/flyscript.css
docs/html/glossary.html
docs/html/hacking.html
docs/html/index.html
docs/html/install.html
docs/html/install_details.html
docs/html/profiler.html
docs/html/profiler_columns.html
docs/html/rb-logo.png
docs/html/rest_apis.html
docs/html/ridl.css
docs/html/service.html
docs/html/shark.html
docs/html/timeutils.html
docs/html/tutorial-1.pcap
docs/html/tutorial_profiler.html
docs/html/tutorial_shark.html
docs/html/tutorials.html
examples/test_examples.py
examples/profiler/alerter.py
examples/profiler/devices.py
examples/profiler/flowlist.py
examples/profiler/identity_report.py
examples/profiler/myreport.py
examples/profiler/percentile.py
examples/profiler/timeseries.py
examples/profiler/top_ports.py
examples/profiler/traffic_flowlist.py
examples/profiler/traffic_summary.py
examples/profiler/traffic_timeseries.py
examples/profiler/wan_report.py
examples/shark/backup_restore.py
examples/shark/control_job.py
examples/shark/create_clip.py
examples/shark/create_job.py
examples/shark/create_job_ex.py
examples/shark/create_view.py
examples/shark/create_view_ex.py
examples/shark/export.py
examples/shark/readview.py
examples/shark/shark_info.py
flyscript.egg-info/PKG-INFO
flyscript.egg-info/SOURCES.txt
flyscript.egg-info/dependency_links.txt
flyscript.egg-info/requires.txt
flyscript.egg-info/top_level.txt
