Metadata-Version: 1.1
Name: flyscript
Version: 0.6.1
Summary: Riverbed FlyScript library for interacting with Riverbed devices
Home-page: https://splash.riverbed.com/docs/DOC-1464
Author: Riverbed Technology
Author-email: cwhite@riverbed.com
License: Copyright (c) 2013 Riverbed Technology, Inc.
